emv/__init__.py
emv/cap.py
emv/card.py
emv/exc.py
emv/transmission.py
emv/util.py
emv/command/__init__.py
emv/command/client.py
emv/protocol/__init__.py
emv/protocol/command.py
emv/protocol/data.py
emv/protocol/data_elements.py
emv/protocol/response.py
emv/protocol/structures.py
emv-1.0.14.dist-info/LICENSE
emv-1.0.14.dist-info/METADATA
emv-1.0.14.dist-info/WHEEL
emv-1.0.14.dist-info/entry_points.txt
emv-1.0.14.dist-info/top_level.txt
emv-1.0.14.dist-info/RECORD
