Metadata-Version: 2.1
Name: emv
Version: 1.0.14
Summary: EMV Smartcard Protocol Library
Home-page: https://github.com/russss/python-emv
Author: Russ Garrett
Author-email: russ@garrett.co.uk
License: MIT
Keywords: smartcard emv payment
Platform: UNKNOWN
Classifier: Development Status :: 4 - Beta
Classifier: License :: OSI Approved :: MIT License
Classifier: Programming Language :: Python :: 3
Requires-Python: >=3.4
License-File: LICENSE
Requires-Dist: enum-compat (==0.0.3)
Requires-Dist: argparse (==1.4.0)
Requires-Dist: pyscard (==2.0.0)
Requires-Dist: pycountry (==20.7.3)
Requires-Dist: terminaltables (==3.1.0)
Requires-Dist: click (==7.1.2)
